<?xml version="1.0" encoding="UTF-8"?>

<Configuration hierarchy="cl" description="Chile"
               xmlns="https://focus_shift.de/jollyday/schema/holiday"
               xmlns:xsi="http://www.w3.org/2001/XMLSchema-instance"
               xsi:schemaLocation="https://focus_shift.de/jollyday/schema/holiday https://focus_shift.de/jollyday/schema/holiday/holiday.xsd">
  <Holidays>
    <Fixed month="JANUARY" day="1" descriptionPropertiesKey="NEW_YEAR"/>
    <Fixed month="JANUARY" day="17" validFrom="2010" validTo="2010" descriptionPropertiesKey="ELECTION_DAY"/>
    <Fixed month="MAY" day="1" descriptionPropertiesKey="LABOUR_DAY"/>
    <Fixed month="MAY" day="21" descriptionPropertiesKey="NAVY_DAY"/>
    <Fixed month="JUNE" day="28" descriptionPropertiesKey="ST_PETER_PAUL"/>
    <Fixed month="JULY" day="16" validFrom="2007" descriptionPropertiesKey="VIRGIN_CARMEN"/>
    <Fixed month="AUGUST" day="15" descriptionPropertiesKey="ASSUMPTION_MARY"/>
    <Fixed month="SEPTEMBER" day="18" descriptionPropertiesKey="NATIONAL_DAY"/>
    <Fixed month="SEPTEMBER" day="19" descriptionPropertiesKey="ARMY_DAY"/>
    <Fixed month="OCTOBER" day="11" descriptionPropertiesKey="COLUMBUS_DAY"/>
    <Fixed month="OCTOBER" day="31" validFrom="2008" descriptionPropertiesKey="REFORMATION_DAY"/>
    <Fixed month="NOVEMBER" day="1" descriptionPropertiesKey="ALL_SAINTS"/>
    <Fixed month="DECEMBER" day="8" descriptionPropertiesKey="IMMACULATE_CONCEPTION"/>
    <Fixed month="DECEMBER" day="25" descriptionPropertiesKey="CHRISTMAS"/>
    <Fixed month="DECEMBER" day="31" descriptionPropertiesKey="NEW_YEARS_EVE"/>
    <ChristianHoliday type="EASTER" descriptionPropertiesKey="christian.EASTER"/>
    <ChristianHoliday type="GOOD_FRIDAY" descriptionPropertiesKey="christian.GOOD_FRIDAY"/>
    <ChristianHoliday type="EASTER_SATURDAY" descriptionPropertiesKey="christian.EASTER_SATURDAY"/>
    <ChristianHoliday type="CORPUS_CHRISTI" descriptionPropertiesKey="christian.CORPUS_CHRISTI" validTo="2006"/>
  </Holidays>
</Configuration>
